pdf_information/__init__.py
pdf_information/encrypted.py
pdf_information/mapping.py
pdf_information/pdf_info.py
pdf_information/snake_case.py
pdf_information/value_conversion.py
pdf_information/version.py
pdf_information-0.0.1.dist-info/METADATA
pdf_information-0.0.1.dist-info/WHEEL
pdf_information-0.0.1.dist-info/entry_points.txt
pdf_information-0.0.1.dist-info/top_level.txt
pdf_information-0.0.1.dist-info/RECORD
